LICENSE.txt
setup.py
AAEEGGOOSS.egg-info/PKG-INFO
AAEEGGOOSS.egg-info/SOURCES.txt
AAEEGGOOSS.egg-info/dependency_links.txt
AAEEGGOOSS.egg-info/top_level.txt
code/__init__.py